crowdstrike/__init__.py
crowdstrike/detects.py
crowdstrike/event_streams.py
crowdstrike/hostgroup.py
crowdstrike/hosts.py
crowdstrike/incidents.py
crowdstrike/intel.py
crowdstrike/rtr.py
crowdstrike/rtr_admin.py
crowdstrike/sensor_download.py
crowdstrike/utilities.py
crowdstrike-0.0.5.dist-info/WHEEL
crowdstrike-0.0.5.dist-info/METADATA
crowdstrike-0.0.5.dist-info/RECORD
