Metadata-Version: 2.1
Name: crowdstrike
Version: 0.0.5
Summary: Python interface to the Crowdstrike API
Home-page: https://github.com/yaleman/crowdstrike_api
License: MIT
Keywords: api,crowdstrike
Author: James Hodgkinson
Author-email: james@terminaloutcomes.com
Requires-Python: >=3.7,<4.0
Classifier: Development Status :: 4 - Beta
Classifier: License :: OSI Approved :: MIT License
Classifier: Operating System :: OS Independent
Classifier: Programming Language :: Python :: 3
Classifier: Programming Language :: Python :: 3.10
Classifier: Programming Language :: Python :: 3.7
Classifier: Programming Language :: Python :: 3.8
Classifier: Programming Language :: Python :: 3.9
Requires-Dist: loguru (>=0.6.0,<0.7.0)
Requires-Dist: requests-oauthlib (>=1.3.1,<2.0.0)
Project-URL: Repository, https://github.com/yaleman/crowdstrike_api
